janus_client/__init__.py
janus_client/client.py
janus_dtnaas_client-0.1.dist-info/METADATA
janus_dtnaas_client-0.1.dist-info/WHEEL
janus_dtnaas_client-0.1.dist-info/top_level.txt
janus_dtnaas_client-0.1.dist-info/RECORD
