Metadata-Version: 2.4
Name: janus-dtnaas-client
Version: 0.1
Summary: ESnet Janus Client
Home-page: https://github.com/disprosium8/janus-client
Author: Ezra Kissel
Keywords: dtn rest controller
Classifier: Development Status :: 5 - Production/Stable
Classifier: Intended Audience :: Developers
Classifier: Topic :: Software Development :: Libraries :: Application Frameworks
Classifier: License :: OSI Approved :: MIT License
Classifier: Programming Language :: Python :: 2
Classifier: Programming Language :: Python :: 2.7
Classifier: Programming Language :: Python :: 3
Classifier: Programming Language :: Python :: 3.4
Classifier: Programming Language :: Python :: 3.5
Classifier: Programming Language :: Python :: 3.6
Requires-Dist: requests
Dynamic: author
Dynamic: classifier
Dynamic: home-page
Dynamic: keywords
Dynamic: requires-dist
Dynamic: summary
